{ "questions" : [
                 {
                 "id" : 1,
                 "description" : "Правда или ложь: в Google Analytics можно посмотреть, сколько посетителей находится на сайте прямо сейчас.",
                 "variants" : [
                               {
                               "description" : "Правда.",
                               "is_correct" : true
                               },
                               {
                               "description" : "Ложь.",
                               "is_correct" : false
                               }
                               ]
                 },
                 {
                 "id" : 2,
                 "description" : "Возможно ли сделать так, чтобы в отчете “Все страницы” отображались названия страниц, отличные от действительных названий страниц?",
                 "variants" : [
                               {
                               "description" : "Вам следует попросить вашего вебмастера поменять настройки сервера, чтобы включить требуемые параметры.",
                               "is_correct" : false
                               },
                               {
                               "description" : "Да, вы можете переименовать страницы, введя желаемый URI в вызов _link().",
                               "is_correct" : false
                               },
                               {
                               "description" : "Да, вы можете переименовать страницы, введя желаемый URI в вызов _trackPageview().",
                               "is_correct" : true
                               },
                               {
                               "description" : "Нет, это невозможно.",
                               "is_correct" : false
                               }
                               ]
                 },
                 {
                 "id" : 3,
                 "description" : "У вашего сайта есть три раздела, и вы хотите иметь взгляд на данные как для всего сайта, так и для каждого раздела. Как следует поступить?",
                 "variants" : [
                               {
                               "description" : "Один аккаунт , который включает представление (профиль) для всего сайта, и дублирующие представления, в каждом из которых настроен включающий фильтр для отслеживания каждого раздела.",
                               "is_correct" : true
                               },
                               {
                               "description" : "По одному аккаунту для каждого раздела, и еще один аккаунт – для всего сайта.",
                               "is_correct" : false
                               },
                               { 
                               "description" : "Один аккаунт, который включает представление для всего сайта, и второе представление с включающим фильтром для разделов.",
                               "is_correct" : false
                               },
                               {
                               "description" : "Это невозможно.",
                               "is_correct" : false
                               }
                               ]
                 },
                 {
                 "id" : 4,
                 "description" : "Для чего нужен _setVar() метод?",
                 "variants" : [
                               {
                               "description" : "Для отслеживания транзакций электронной торговли",
                               "is_correct" : false
                               },
                               {
                               "description" : "Для создания специальных ярлыков для URL",
                               "is_correct" : false
                               },
                               {
                               "description" : "Для создания специальных пользовательских сегментов",
                               "is_correct" : true
                               },
                               {
                               "description" : "Для отслеживания посещений, которые охватывают несколько доменов",
                               "is_correct" : false
                               }
                               ]
                 }
                 ]
}
